mapper/__init__.py
mapper/__version__.py
mapper/app/__init__.py
mapper/app/mapper.py
mapper/app/text_cleaner.py
mapper/app/word_transformation.py
mapper/scripts/__init__.py
mapper/scripts/setup_nltk.py
mapper/services/__init__.py
mapper/services/word_similarity.py
mapper/utils/__init__.py
mapper/utils/common.py
mapper/utils/word_utils.py
auto_mapper-0.1.2.dist-info/LICENSE
auto_mapper-0.1.2.dist-info/METADATA
auto_mapper-0.1.2.dist-info/WHEEL
auto_mapper-0.1.2.dist-info/entry_points.txt
auto_mapper-0.1.2.dist-info/top_level.txt
auto_mapper-0.1.2.dist-info/RECORD
