Metadata-Version: 2.1
Name: auto-mapper
Version: 0.1.2
Summary: An auto mapper that accepts a list of string and a list of objects of the format {'code', 'name'} and return a list of object where each 'code' is mapped to the most similar strings from the list of strings
Home-page: https://pypi.org/project/auto-mapper/
Author: Ilyasse Benrkia
Author-email: benrkyailyass@gmail.com
License: MIT
Keywords: auto,mapper,mapping,text processing,text similarity
Platform: UNKNOWN
Classifier: Intended Audience :: Developers
Classifier: License :: OSI Approved :: MIT License
Classifier: Operating System :: OS Independent
Classifier: Programming Language :: Python
Classifier: Programming Language :: Python :: 3
Classifier: Programming Language :: Python :: 3.7
Classifier: Programming Language :: Python :: 3.8
Requires-Python: >=3.7
Requires-Dist: importlib-metadata (==1.6.1)
Requires-Dist: nltk (==3.5)
Requires-Dist: unidecode (==1.1.1)
Requires-Dist: requests (==2.23.0)
